ohdsi_webapi/__init__.py
ohdsi_webapi/auth/__init__.py
ohdsi_webapi/cache.py
ohdsi_webapi/client.py
ohdsi_webapi/env.py
ohdsi_webapi/exceptions.py
ohdsi_webapi/http.py
ohdsi_webapi/models/cohort.py
ohdsi_webapi/models/concept_set.py
ohdsi_webapi/models/info.py
ohdsi_webapi/models/source.py
ohdsi_webapi/models/vocabulary.py
ohdsi_webapi/services/cohort_definition.py
ohdsi_webapi/services/concept_sets.py
ohdsi_webapi/services/info.py
ohdsi_webapi/services/jobs.py
ohdsi_webapi/services/source.py
ohdsi_webapi/services/sources.py
ohdsi_webapi/services/vocabulary.py
ohdsi_webapi/utils/polling.py
ohdsi_webapi_client-0.4.2.dist-info/METADATA
ohdsi_webapi_client-0.4.2.dist-info/WHEEL
ohdsi_webapi_client-0.4.2.dist-info/RECORD
