Metadata-Version: 2.3
Name: ohdsi-webapi-client
Version: 0.4.2
Summary: Python client for OHDSI WebAPI (MVP: info, sources, vocabulary, concept sets, cohorts).
License: Apache-2.0
Keywords: OHDSI,WebAPI,OMOP,ETL,Cohort,Healthcare
Author: Your Name
Author-email: you@example.com
Requires-Python: >=3.11,<4.0
Classifier: Development Status :: 3 - Alpha
Classifier: Intended Audience :: Science/Research
Classifier: License :: OSI Approved :: Apache Software License
Classifier: Programming Language :: Python :: 3
Classifier: Programming Language :: Python :: 3.11
Classifier: Programming Language :: Python :: 3.12
Classifier: Programming Language :: Python :: 3.13
Classifier: Programming Language :: Python :: 3 :: Only
Classifier: Topic :: Scientific/Engineering :: Medical Science Apps.
Provides-Extra: cli
Provides-Extra: pandas
Requires-Dist: httpx[http2] (>=0.27,<0.28)
Requires-Dist: ohdsi-cohort-schemas (==0.4.1)
Requires-Dist: pydantic (>=2.7,<3.0)
Requires-Dist: python-dotenv (>=1.1.1,<2.0.0)
Requires-Dist: tenacity (>=8.2,<9.0)
Requires-Dist: typing-extensions (>=4.11,<5.0)
Project-URL: Homepage, https://github.com/clsweeting/ohdsi-webapi
Project-URL: Repository, https://github.com/clsweeting/ohdsi-webapi
